setup.py
wax/__init__.py
wax/__main__.py
wax/common_util.py
wax/index.py
wax/jsonschema_util.py
wax/kotlin_util.py
wax/load_config.py
wax/load_func.py
wax/load_swagger.py
wax/main.py
wax/mock_api.py
wax/pack_util.py
wax/pql.py
wax/service.py
wax/tag_api.py
wax/zip_data.py
wax/lessweb/__init__.py
wax/lessweb/application.py
wax/lessweb/bridge.py
wax/lessweb/context.py
wax/lessweb/model.py
wax/lessweb/pluginproto.py
wax/lessweb/storage.py
wax/lessweb/typehint.py
wax/lessweb/utils.py
wax/lessweb/webapi.py
wax/lessweb/plugin/__init__.py
wax/lessweb/plugin/dbplugin.py
wax/lessweb/plugin/redisplugin.py
wax_mock.egg-info/PKG-INFO
wax_mock.egg-info/SOURCES.txt
wax_mock.egg-info/dependency_links.txt
wax_mock.egg-info/entry_points.txt
wax_mock.egg-info/requires.txt
wax_mock.egg-info/top_level.txt