Metadata-Version: 1.0
Name: wax-mock
Version: 0.4.1
Summary: Mock server with Swagger OpenAPI3 JSON
Home-page: https://pypi.python.org/project/wax-mock
Author: qorzj
Author-email: inull@qq.com
License: MIT
Keywords: mock swagger openapi openapi3
Platform: any
